orm/__init__.py
orm_django-0.0.4.dist-info/LICENSE
orm_django-0.0.4.dist-info/METADATA
orm_django-0.0.4.dist-info/WHEEL
orm_django-0.0.4.dist-info/top_level.txt
orm_django-0.0.4.dist-info/RECORD
