Metadata-Version: 2.1
Name: orm-django
Version: 0.0.4
Summary: A package for using Django ORM standalone in scripts
Author-email: Stamatios Stamou Jr <ssjunior@gmail.com>
Project-URL: Homepage, https://github.com/ssjunior/orm-django
Project-URL: Bug Tracker, https://github.com/ssjunior/orm-django/issues
Classifier: Programming Language :: Python :: 3
Classifier: License :: OSI Approved :: MIT License
Classifier: Operating System :: OS Independent
Requires-Python: >=3.7
License-File: LICENSE
